license_markdown_table/__init__.py
license_markdown_table/license_markdown_table.py
license_markdown_table-0.1.0.dist-info/LICENSE
license_markdown_table-0.1.0.dist-info/WHEEL
license_markdown_table-0.1.0.dist-info/METADATA
license_markdown_table-0.1.0.dist-info/RECORD
